{
  "type": "cdl",
  "project": "epsd2/literary",
  "source": "http://oracc.org/epsd2/literary",
  "license": "This data is released under the CC0 license",
  "license-url": "https://creativecommons.org/publicdomain/zero/1.0/",
  "more-info": "http://oracc.org/doc/opendata/",
  "UTC-timestamp": "2021-12-21T02:43:20",
  "textid": "P254894",
  "cdl": [
    {
      "node": "c",
      "type": "text",
      "id": "P254894.U0",
      "cdl": [
        {
          "node": "d",
          "subtype": "tablet",
          "type": "object",
          "ref": "P254894.x42.1",
          "label": "x42"
        },
        {
          "node": "d",
          "subtype": "obverse",
          "type": "surface",
          "ref": "P254894.o.2",
          "label": "o"
        },
        {
          "node": "c",
          "type": "discourse",
          "subtype": "body",
          "id": "P254894.U1",
          "cdl": [
            {
              "node": "c",
              "type": "sentence",
              "implicit": "yes",
              "id": "P254894.U2",
              "label": "o 1 - o 9",
              "cdl": [
                {
                  "node": "d",
                  "type": "line-start",
                  "ref": "P254894.3",
                  "n": "1",
                  "label": "o 1"
                },
                {
                  "node": "l",
                  "frag": "inim",
                  "id": "P254894.l00c05",
                  "ref": "P254894.3.1",
                  "inst": "inim[word]",
                  "sig": "@epsd2/literary%sux:inim=inim[word//word]N'N$inim/inim#~",
                  "f": {
                    "lang": "sux",
                    "form": "inim",
                    "delim": "",
                    "gdl": [
                      {
                        "v": "inim",
                        "id": "P254894.3.1.0"
                      }
                    ],
                    "cf": "inim",
                    "gw": "word",
                    "sense": "word",
                    "norm0": "inim",
                    "pos": "N",
                    "epos": "N",
                    "base": "inim",
                    "morph": "~"
                  },
                  "props": [
                    {
                      "name": "field",
                      "group": "env",
                      "ngram": "-1",
                      "ref": "P254894.3.1"
                    },
                    {
                      "name": "discourse",
                      "group": "env",
                      "value": "body",
                      "ngram": "-1",
                      "ref": "P254894.3.1"
                    }
                  ]
                },
                {
                  "node": "l",
                  "frag": "ab-ba-še₃",
                  "id": "P254894.l00c06",
                  "ref": "P254894.3.2",
                  "inst": "abba[father]",
                  "sig": "@epsd2/literary%sux:ab-ba-še₃=abba[father//father]N'N$abba,eše/ab-ba#~,eše",
                  "f": {
                    "lang": "sux",
                    "form": "ab-ba-še₃",
                    "gdl": [
                      {
                        "v": "ab",
                        "id": "P254894.3.2.0",
                        "delim": "-"
                      },
                      {
                        "v": "ba",
                        "id": "P254894.3.2.1",
                        "delim": "-"
                      },
                      {
                        "v": "še₃",
                        "id": "P254894.3.2.2"
                      }
                    ],
                    "cf": "abba",
                    "gw": "father",
                    "sense": "father",
                    "norm0": "abba,eše",
                    "pos": "N",
                    "epos": "N",
                    "base": "ab-ba",
                    "morph": "~,eše"
                  },
                  "props": [
                    {
                      "name": "field",
                      "group": "env",
                      "ngram": "-1",
                      "ref": "P254894.3.2"
                    },
                    {
                      "name": "discourse",
                      "group": "env",
                      "value": "body",
                      "ngram": "-1",
                      "ref": "P254894.3.2"
                    }
                  ]
                },
                {
                  "node": "d",
                  "type": "line-start",
                  "ref": "P254894.4",
                  "n": "2",
                  "label": "o 2"
                },
                {
                  "node": "l",
                  "frag": "ŋizzal",
                  "id": "P254894.l00c07",
                  "ref": "P254894.4.1",
                  "inst": "ŋizzal[ear]",
                  "sig": "@epsd2/literary%sux:ŋizzal=ŋizzal[ear//ear]N'N$ŋizzal/ŋizzal#~",
                  "f": {
                    "lang": "sux",
                    "form": "ŋizzal",
                    "delim": "",
                    "gdl": [
                      {
                        "v": "ŋizzal",
                        "id": "P254894.4.1.0"
                      }
                    ],
                    "cf": "ŋizzal",
                    "gw": "ear",
                    "sense": "ear",
                    "norm0": "ŋizzal",
                    "pos": "N",
                    "epos": "N",
                    "base": "ŋizzal",
                    "morph": "~"
                  },
                  "props": [
                    {
                      "name": "field",
                      "group": "env",
                      "ngram": "-1",
                      "ref": "P254894.4.1"
                    },
                    {
                      "name": "discourse",
                      "group": "env",
                      "value": "body",
                      "ngram": "-1",
                      "ref": "P254894.4.1"
                    }
                  ]
                },
                {
                  "node": "l",
                  "frag": "ak-de₃",
                  "id": "P254894.l00c08",
                  "ref": "P254894.4.2",
                  "inst": "ak[do]",
                  "sig": "@epsd2/literary%sux:ak-de₃=ak[do//do]V/t'V/t$ak;de/ak#~;de",
                  "f": {
                    "lang": "sux",
                    "form": "ak-de₃",
                    "delim": "",
                    "gdl": [
                      {
                        "v": "ak",
                        "id": "P254894.4.2.0",
                        "delim": "-"
                      },
                      {
                        "v": "de₃",
                        "id": "P254894.4.2.1"
                      }
                    ],
                    "cf": "ak",
                    "gw": "do",
                    "sense": "do",
                    "norm0": "ak;de",
                    "pos": "V/t",
                    "epos": "V/t",
                    "base": "ak",
                    "morph": "~;de"
                  },
                  "props": [
                    {
                      "name": "field",
                      "group": "env",
                      "ngram": "-1",
                      "ref": "P254894.4.2"
                    },
                    {
                      "name": "discourse",
                      "group": "env",
                      "value": "body",
                      "ngram": "-1",
                      "ref": "P254894.4.2"
                    }
                  ]
                },
                {
                  "node": "l",
                  "frag": "u₃-te-qi₂-a-am",
                  "id": "P254894.l00c09",
                  "ref": "P254894.4.3",
                  "inst": "***",
                  "f": {
                    "lang": "akk-x-oldbab",
                    "form": "u₃-te-qi₂-a-am",
                    "gdl": [
                      {
                        "v": "u₃",
                        "id": "P254894.4.3.0",
                        "queried": "1",
                        "delim": "-"
                      },
                      {
                        "v": "te",
                        "id": "P254894.4.3.1",
                        "delim": "-"
                      },
                      {
                        "v": "qi₂",
                        "id": "P254894.4.3.2",
                        "delim": "-"
                      },
                      {
                        "v": "a",
                        "id": "P254894.4.3.3",
                        "delim": "-"
                      },
                      {
                        "v": "am",
                        "id": "P254894.4.3.4"
                      }
                    ]
                  },
                  "props": [
                    {
                      "name": "field",
                      "group": "env",
                      "ngram": "-1",
                      "ref": "P254894.4.3"
                    },
                    {
                      "name": "discourse",
                      "group": "env",
                      "value": "body",
                      "ngram": "-1",
                      "ref": "P254894.4.3"
                    }
                  ]
                },
                {
                  "node": "d",
                  "type": "nonw",
                  "ref": ""
                },
                {
                  "node": "d",
                  "type": "line-start",
                  "ref": "P254894.5",
                  "n": "3",
                  "label": "o 3"
                },
                {
                  "node": "l",
                  "frag": "ni₂",
                  "id": "P254894.l00c0a",
                  "ref": "P254894.5.1",
                  "inst": "ni[self]",
                  "sig": "@epsd2/literary%sux:ni₂=ni[self//self]RP'RP$ni/ni₂#~",
                  "f": {
                    "lang": "sux",
                    "form": "ni₂",
                    "delim": "",
                    "gdl": [
                      {
                        "v": "ni₂",
                        "id": "P254894.5.1.0"
                      }
                    ],
                    "cf": "ni",
                    "gw": "self",
                    "sense": "self",
                    "norm0": "ni",
                    "pos": "RP",
                    "epos": "RP",
                    "base": "ni₂",
                    "morph": "~"
                  },
                  "props": [
                    {
                      "name": "field",
                      "group": "env",
                      "ngram": "-1",
                      "ref": "P254894.5.1"
                    },
                    {
                      "name": "discourse",
                      "group": "env",
                      "value": "body",
                      "ngram": "-1",
                      "ref": "P254894.5.1"
                    }
                  ]
                },
                {
                  "node": "c",
                  "type": "phrase",
                  "tag": "phr",
                  "id": "P254894.U4",
                  "ref": "P254894.ls00000",
                  "cdl": [
                    {
                      "node": "l",
                      "frag": "šu-a",
                      "id": "P254894.l00c0b",
                      "ref": "P254894.5.2",
                      "inst": "šu[hand]",
                      "sig": "@epsd2/literary%sux:šu-a=šu[hand//hand]N'N$šu,a/šu#~,a",
                      "f": {
                        "lang": "sux",
                        "form": "šu-a",
                        "delim": "",
                        "gdl": [
                          {
                            "v": "šu",
                            "id": "P254894.5.2.0",
                            "delim": "-"
                          },
                          {
                            "v": "a",
                            "id": "P254894.5.2.1"
                          }
                        ],
                        "cf": "šu",
                        "gw": "hand",
                        "sense": "hand",
                        "norm0": "šu,a",
                        "pos": "N",
                        "epos": "N",
                        "base": "šu",
                        "morph": "~,a"
                      },
                      "props": [
                        {
                          "name": "field",
                          "group": "env",
                          "ngram": "-1",
                          "ref": "P254894.5.2"
                        },
                        {
                          "name": "discourse",
                          "group": "env",
                          "value": "body",
                          "ngram": "-1",
                          "ref": "P254894.5.2"
                        }
                      ]
                    },
                    {
                      "node": "l",
                      "frag": "gi₄-gi₄-de₃",
                      "id": "P254894.l00c0c",
                      "ref": "P254894.5.3",
                      "inst": "gi[turn]",
                      "sig": "@epsd2/literary%sux:gi₄-gi₄-de₃=gi[turn//turn]V/i'V/i$gi;de/gi₄-gi₄#~;de",
                      "f": {
                        "lang": "sux",
                        "form": "gi₄-gi₄-de₃",
                        "delim": "",
                        "gdl": [
                          {
                            "v": "gi₄",
                            "id": "P254894.5.3.0",
                            "delim": "-"
                          },
                          {
                            "v": "gi₄",
                            "id": "P254894.5.3.1",
                            "delim": "-"
                          },
                          {
                            "v": "de₃",
                            "id": "P254894.5.3.2"
                          }
                        ],
                        "cf": "gi",
                        "gw": "turn",
                        "sense": "turn",
                        "norm0": "gi;de",
                        "pos": "V/i",
                        "epos": "V/i",
                        "base": "gi₄-gi₄",
                        "morph": "~;de"
                      },
                      "props": [
                        {
                          "name": "field",
                          "group": "env",
                          "ngram": "-1",
                          "ref": "P254894.5.3"
                        },
                        {
                          "name": "discourse",
                          "group": "env",
                          "value": "body",
                          "ngram": "-1",
                          "ref": "P254894.5.3"
                        }
                      ]
                    }
                  ]
                },
                {
                  "node": "l",
                  "frag": "ra-ma-an-šu",
                  "id": "P254894.l00c0d",
                  "ref": "P254894.5.4",
                  "inst": "***",
                  "f": {
                    "lang": "akk-x-oldbab",
                    "form": "ra-ma-an-šu",
                    "delim": "",
                    "gdl": [
                      {
                        "v": "ra",
                        "id": "P254894.5.4.0",
                        "delim": "-"
                      },
                      {
                        "v": "ma",
                        "id": "P254894.5.4.1",
                        "delim": "-"
                      },
                      {
                        "v": "an",
                        "id": "P254894.5.4.2",
                        "delim": "-"
                      },
                      {
                        "v": "šu",
                        "id": "P254894.5.4.3"
                      }
                    ]
                  },
                  "props": [
                    {
                      "name": "field",
                      "group": "env",
                      "ngram": "-1",
                      "ref": "P254894.5.4"
                    },
                    {
                      "name": "discourse",
                      "group": "env",
                      "value": "body",
                      "ngram": "-1",
                      "ref": "P254894.5.4"
                    }
                  ]
                },
                {
                  "node": "l",
                  "frag": "šu-lu-ma-am",
                  "id": "P254894.l00c0e",
                  "ref": "P254894.5.5",
                  "inst": "***",
                  "f": {
                    "lang": "akk-x-oldbab",
                    "form": "šu-lu-ma-am",
                    "gdl": [
                      {
                        "v": "šu",
                        "id": "P254894.5.5.0",
                        "delim": "-"
                      },
                      {
                        "v": "lu",
                        "id": "P254894.5.5.1",
                        "delim": "-"
                      },
                      {
                        "v": "ma",
                        "id": "P254894.5.5.2",
                        "delim": "-"
                      },
                      {
                        "v": "am",
                        "id": "P254894.5.5.3"
                      }
                    ]
                  },
                  "props": [
                    {
                      "name": "field",
                      "group": "env",
                      "ngram": "-1",
                      "ref": "P254894.5.5"
                    },
                    {
                      "name": "discourse",
                      "group": "env",
                      "value": "body",
                      "ngram": "-1",
                      "ref": "P254894.5.5"
                    }
                  ]
                },
                {
                  "node": "d",
                  "type": "nonw",
                  "ref": ""
                },
                {
                  "node": "d",
                  "type": "nonx",
                  "ref": "P254894.6",
                  "strict": "1",
                  "extent": "1",
                  "scope": "line",
                  "state": "ruling"
                },
                {
                  "node": "d",
                  "type": "line-start",
                  "ref": "P254894.7",
                  "n": "4",
                  "label": "o 4"
                },
                {
                  "node": "l",
                  "frag": "dumu",
                  "id": "P254894.l00c0f",
                  "ref": "P254894.7.1",
                  "inst": "dumu[child]",
                  "sig": "@epsd2/literary%sux:dumu=dumu[child//child, son, daughter]N'N$dumu/dumu#~",
                  "f": {
                    "lang": "sux",
                    "form": "dumu",
                    "delim": "",
                    "gdl": [
                      {
                        "v": "dumu",
                        "id": "P254894.7.1.0"
                      }
                    ],
                    "cf": "dumu",
                    "gw": "child",
                    "sense": "child, son, daughter",
                    "norm0": "dumu",
                    "pos": "N",
                    "epos": "N",
                    "base": "dumu",
                    "morph": "~"
                  },
                  "props": [
                    {
                      "name": "field",
                      "group": "env",
                      "ngram": "-1",
                      "ref": "P254894.7.1"
                    },
                    {
                      "name": "discourse",
                      "group": "env",
                      "value": "body",
                      "ngram": "-1",
                      "ref": "P254894.7.1"
                    }
                  ]
                },
                {
                  "node": "l",
                  "frag": "ama-ni-ir",
                  "id": "P254894.l00c10",
                  "ref": "P254894.7.2",
                  "inst": "ama[mother]",
                  "sig": "@epsd2/literary%sux:ama-ni-ir=ama[mother//mother]N'N$ama,ani.ra/ama#~,ani.ra",
                  "f": {
                    "lang": "sux",
                    "form": "ama-ni-ir",
                    "delim": "",
                    "gdl": [
                      {
                        "v": "ama",
                        "id": "P254894.7.2.0",
                        "delim": "-"
                      },
                      {
                        "v": "ni",
                        "id": "P254894.7.2.1",
                        "delim": "-"
                      },
                      {
                        "v": "ir",
                        "id": "P254894.7.2.2"
                      }
                    ],
                    "cf": "ama",
                    "gw": "mother",
                    "sense": "mother",
                    "norm0": "ama,ani.ra",
                    "pos": "N",
                    "epos": "N",
                    "base": "ama",
                    "morph": "~,ani.ra"
                  },
                  "props": [
                    {
                      "name": "field",
                      "group": "env",
                      "ngram": "-1",
                      "ref": "P254894.7.2"
                    },
                    {
                      "name": "discourse",
                      "group": "env",
                      "value": "body",
                      "ngram": "-1",
                      "ref": "P254894.7.2"
                    }
                  ]
                },
                {
                  "node": "l",
                  "frag": "sun₅-na",
                  "id": "P254894.l00c11",
                  "ref": "P254894.7.3",
                  "inst": "sun[humble]",
                  "sig": "@epsd2/literary%sux:sun₅-na=sun[humble//(to be) humble]V/i'V/i$sun;a/sun₅+-na=n.a#~;a",
                  "f": {
                    "lang": "sux",
                    "form": "sun₅-na",
                    "delim": "",
                    "gdl": [
                      {
                        "v": "sun₅",
                        "id": "P254894.7.3.0",
                        "delim": "-"
                      },
                      {
                        "v": "na",
                        "id": "P254894.7.3.1"
                      }
                    ],
                    "cf": "sun",
                    "gw": "humble",
                    "sense": "(to be) humble",
                    "norm0": "sun;a",
                    "pos": "V/i",
                    "epos": "V/i",
                    "base": "sun₅",
                    "cont": "-na=n.a",
                    "morph": "~;a"
                  },
                  "props": [
                    {
                      "name": "field",
                      "group": "env",
                      "ngram": "-1",
                      "ref": "P254894.7.3"
                    },
                    {
                      "name": "discourse",
                      "group": "env",
                      "value": "body",
                      "ngram": "-1",
                      "ref": "P254894.7.3"
                    }
                  ]
                },
                {
                  "node": "c",
                  "type": "phrase",
                  "tag": "phr",
                  "id": "P254894.U5",
                  "ref": "P254894.ls00001",
                  "cdl": [
                    {
                      "node": "l",
                      "frag": "<ni₂>",
                      "id": "P254894.l00c12",
                      "ref": "P254894.7.4",
                      "inst": "ni[aura]",
                      "sig": "@epsd2/literary%sux:ni₂=ni[fear//aura]N'N$ni/ni₂#~",
                      "f": {
                        "lang": "sux",
                        "form": "ni₂",
                        "delim": "",
                        "gdl": [
                          {
                            "v": "ni₂",
                            "id": "P254894.7.4.0",
                            "statusStart": "P254894.7.4.0",
                            "o": ">"
                          }
                        ],
                        "cf": "ni",
                        "gw": "fear",
                        "sense": "aura",
                        "norm0": "ni",
                        "pos": "N",
                        "epos": "N",
                        "base": "ni₂",
                        "morph": "~"
                      },
                      "props": [
                        {
                          "name": "field",
                          "group": "env",
                          "ngram": "-1",
                          "ref": "P254894.7.4"
                        },
                        {
                          "name": "discourse",
                          "group": "env",
                          "value": "body",
                          "ngram": "-1",
                          "ref": "P254894.7.4"
                        }
                      ]
                    },
                    {
                      "node": "l",
                      "frag": "teŋ₃-ŋa₂",
                      "id": "P254894.l00c13",
                      "ref": "P254894.7.5",
                      "inst": "teŋ[approach]",
                      "sig": "@epsd2/literary%sux:teŋ₃-ŋa₂=teŋ[near//to approach]V/i'V/t$teŋ;a/teŋ₃+-ŋa₂=ŋ.a#~;a",
                      "f": {
                        "lang": "sux",
                        "form": "teŋ₃-ŋa₂",
                        "gdl": [
                          {
                            "v": "teŋ₃",
                            "id": "P254894.7.5.0",
                            "delim": "-"
                          },
                          {
                            "v": "ŋa₂",
                            "id": "P254894.7.5.1"
                          }
                        ],
                        "cf": "teŋ",
                        "gw": "near",
                        "sense": "to approach",
                        "norm0": "teŋ;a",
                        "pos": "V/i",
                        "epos": "V/t",
                        "base": "teŋ₃",
                        "cont": "-ŋa₂=ŋ.a",
                        "morph": "~;a"
                      },
                      "props": [
                        {
                          "name": "field",
                          "group": "env",
                          "ngram": "-1",
                          "ref": "P254894.7.5"
                        },
                        {
                          "name": "discourse",
                          "group": "env",
                          "value": "body",
                          "ngram": "-1",
                          "ref": "P254894.7.5"
                        }
                      ]
                    }
                  ]
                },
                {
                  "node": "d",
                  "type": "line-start",
                  "ref": "P254894.8",
                  "n": "5",
                  "label": "o 5"
                },
                {
                  "node": "l",
                  "frag": "nam-ab-ba",
                  "id": "P254894.l00c14",
                  "ref": "P254894.8.1",
                  "inst": "namabba[old age]",
                  "sig": "@epsd2/literary%sux:nam-ab-ba=namabba[age//old age]N'N$namabba/nam-ab-ba#~",
                  "f": {
                    "lang": "sux",
                    "form": "nam-ab-ba",
                    "delim": "",
                    "gdl": [
                      {
                        "v": "nam",
                        "id": "P254894.8.1.0",
                        "delim": "-"
                      },
                      {
                        "v": "ab",
                        "id": "P254894.8.1.1",
                        "delim": "-"
                      },
                      {
                        "v": "ba",
                        "id": "P254894.8.1.2"
                      }
                    ],
                    "cf": "namabba",
                    "gw": "age",
                    "sense": "old age",
                    "norm0": "namabba",
                    "pos": "N",
                    "epos": "N",
                    "base": "nam-ab-ba",
                    "morph": "~"
                  },
                  "props": [
                    {
                      "name": "field",
                      "group": "env",
                      "ngram": "-1",
                      "ref": "P254894.8.1"
                    },
                    {
                      "name": "discourse",
                      "group": "env",
                      "value": "body",
                      "ngram": "-1",
                      "ref": "P254894.8.1"
                    }
                  ]
                },
                {
                  "node": "l",
                  "frag": "šid-de₃",
                  "id": "P254894.l00c15",
                  "ref": "P254894.8.2",
                  "inst": "šid[count]",
                  "sig": "@epsd2/literary%sux:šid-de₃=šid[count//to count]V/t'V/t$šid;e/šid+-de₃=d.e#~;e",
                  "f": {
                    "lang": "sux",
                    "form": "šid-de₃",
                    "gdl": [
                      {
                        "v": "šid",
                        "id": "P254894.8.2.0",
                        "delim": "-"
                      },
                      {
                        "v": "de₃",
                        "id": "P254894.8.2.1"
                      }
                    ],
                    "cf": "šid",
                    "gw": "count",
                    "sense": "to count",
                    "norm0": "šid;e",
                    "pos": "V/t",
                    "epos": "V/t",
                    "base": "šid",
                    "cont": "-de₃=d.e",
                    "morph": "~;e"
                  },
                  "props": [
                    {
                      "name": "field",
                      "group": "env",
                      "ngram": "-1",
                      "ref": "P254894.8.2"
                    },
                    {
                      "name": "discourse",
                      "group": "env",
                      "value": "body",
                      "ngram": "-1",
                      "ref": "P254894.8.2"
                    }
                  ]
                },
                {
                  "node": "d",
                  "type": "nonx",
                  "ref": "P254894.9",
                  "strict": "1",
                  "extent": "1",
                  "scope": "line",
                  "state": "ruling"
                },
                {
                  "node": "d",
                  "type": "line-start",
                  "ref": "P254894.10",
                  "n": "6",
                  "label": "o 6"
                },
                {
                  "node": "l",
                  "frag": "en-na",
                  "id": "P254894.l00c16",
                  "ref": "P254894.10.1",
                  "inst": "enna[until]",
                  "sig": "@epsd2/literary%sux:en-na=enna[until//until, up to]CNJ'CNJ$enna/en-na#~",
                  "f": {
                    "lang": "sux",
                    "form": "en-na",
                    "delim": "",
                    "gdl": [
                      {
                        "v": "en",
                        "id": "P254894.10.1.0",
                        "delim": "-"
                      },
                      {
                        "v": "na",
                        "id": "P254894.10.1.1"
                      }
                    ],
                    "cf": "enna",
                    "gw": "until",
                    "sense": "until, up to",
                    "norm0": "enna",
                    "pos": "CNJ",
                    "epos": "CNJ",
                    "base": "en-na",
                    "morph": "~"
                  },
                  "props": [
                    {
                      "name": "field",
                      "group": "env",
                      "ngram": "-1",
                      "ref": "P254894.10.1"
                    },
                    {
                      "name": "discourse",
                      "group": "env",
                      "value": "body",
                      "ngram": "-1",
                      "ref": "P254894.10.1"
                    }
                  ]
                },
                {
                  "node": "l",
                  "frag": "kug-zu",
                  "id": "P254894.l00c17",
                  "ref": "P254894.10.2",
                  "inst": "kugzu[wise]",
                  "sig": "@epsd2/literary%sux:kug-zu=kugzu[wise//wise]AJ'AJ$kugzu/kug-zu#~",
                  "f": {
                    "lang": "sux",
                    "form": "kug-zu",
                    "delim": "",
                    "gdl": [
                      {
                        "v": "kug",
                        "id": "P254894.10.2.0",
                        "delim": "-"
                      },
                      {
                        "v": "zu",
                        "id": "P254894.10.2.1"
                      }
                    ],
                    "cf": "kugzu",
                    "gw": "wise",
                    "sense": "wise",
                    "norm0": "kugzu",
                    "pos": "AJ",
                    "epos": "AJ",
                    "base": "kug-zu",
                    "morph": "~"
                  },
                  "props": [
                    {
                      "name": "field",
                      "group": "env",
                      "ngram": "-1",
                      "ref": "P254894.10.2"
                    },
                    {
                      "name": "discourse",
                      "group": "env",
                      "value": "body",
                      "ngram": "-1",
                      "ref": "P254894.10.2"
                    }
                  ]
                },
                {
                  "node": "l",
                  "frag": "kug",
                  "id": "P254894.l00c18",
                  "ref": "P254894.10.3",
                  "inst": "kug[metal]",
                  "sig": "@epsd2/literary%sux:kug=kug[metal//metal, silver]N'N$kug/kug#~",
                  "f": {
                    "lang": "sux",
                    "form": "kug",
                    "delim": "",
                    "gdl": [
                      {
                        "v": "kug",
                        "id": "P254894.10.3.0"
                      }
                    ],
                    "cf": "kug",
                    "gw": "metal",
                    "sense": "metal, silver",
                    "norm0": "kug",
                    "pos": "N",
                    "epos": "N",
                    "base": "kug",
                    "morph": "~"
                  },
                  "props": [
                    {
                      "name": "field",
                      "group": "env",
                      "ngram": "-1",
                      "ref": "P254894.10.3"
                    },
                    {
                      "name": "discourse",
                      "group": "env",
                      "value": "body",
                      "ngram": "-1",
                      "ref": "P254894.10.3"
                    }
                  ]
                },
                {
                  "node": "l",
                  "frag": "banda₃{da}na",
                  "id": "P254894.l00c19",
                  "ref": "P254894.10.4",
                  "inst": "banda[junior]",
                  "sig": "@epsd2/literary%sux:banda₃{+da}-na=banda[junior//(to be) junior]V/i'V/i$banda;*a,ani.ak/banda₃{+da}#~;*a,ani.ak",
                  "f": {
                    "lang": "sux",
                    "form": "banda₃{+da}-na",
                    "gdl": [
                      {
                        "v": "banda₃",
                        "id": "P254894.10.4.0"
                      },
                      {
                        "det": "phonetic",
                        "pos": "post",
                        "delim": "-",
                        "seq": [
                          {
                            "v": "da",
                            "id": "P254894.10.4.1"
                          }
                        ]
                      },
                      {
                        "v": "na",
                        "id": "P254894.10.4.2"
                      }
                    ],
                    "cf": "banda",
                    "gw": "junior",
                    "sense": "(to be) junior",
                    "norm0": "banda;*a,ani.ak",
                    "pos": "V/i",
                    "epos": "V/i",
                    "base": "banda₃{+da}",
                    "morph": "~;*a,ani.ak"
                  },
                  "props": [
                    {
                      "name": "field",
                      "group": "env",
                      "ngram": "-1",
                      "ref": "P254894.10.4"
                    },
                    {
                      "name": "discourse",
                      "group": "env",
                      "value": "body",
                      "ngram": "-1",
                      "ref": "P254894.10.4"
                    }
                  ]
                },
                {
                  "node": "d",
                  "type": "line-start",
                  "ref": "P254894.11",
                  "n": "7",
                  "label": "o 7"
                },
                {
                  "node": "l",
                  "frag": "na-ŋa₂-ah",
                  "id": "P254894.l00c1a",
                  "ref": "P254894.11.1",
                  "inst": "naŋah[barbarian]",
                  "sig": "@epsd2/literary%sux:na-ŋa₂-ah=naŋah[fool//barbarian]N'N$naŋah/na-ŋa₂-ah#~",
                  "f": {
                    "lang": "sux",
                    "form": "na-ŋa₂-ah",
                    "delim": "",
                    "gdl": [
                      {
                        "v": "na",
                        "id": "P254894.11.1.0",
                        "delim": "-"
                      },
                      {
                        "v": "ŋa₂",
                        "id": "P254894.11.1.1",
                        "delim": "-"
                      },
                      {
                        "v": "ah",
                        "id": "P254894.11.1.2"
                      }
                    ],
                    "cf": "naŋah",
                    "gw": "fool",
                    "sense": "barbarian",
                    "norm0": "naŋah",
                    "pos": "N",
                    "epos": "N",
                    "base": "na-ŋa₂-ah",
                    "morph": "~"
                  },
                  "props": [
                    {
                      "name": "field",
                      "group": "env",
                      "ngram": "-1",
                      "ref": "P254894.11.1"
                    },
                    {
                      "name": "discourse",
                      "group": "env",
                      "value": "body",
                      "ngram": "-1",
                      "ref": "P254894.11.1"
                    }
                  ]
                },
                {
                  "node": "l",
                  "frag": "a₂-aš₂",
                  "id": "P254894.l00c1b",
                  "ref": "P254894.11.2",
                  "inst": "aʾaš[wish]",
                  "sig": "@epsd2/literary%sux:a₂-aš₂=aʾaš[wish//wish, desire]N'N$aʾaš/a₂-aš₂#~",
                  "f": {
                    "lang": "sux",
                    "form": "a₂-aš₂",
                    "delim": "",
                    "gdl": [
                      {
                        "v": "a₂",
                        "id": "P254894.11.2.0",
                        "delim": "-"
                      },
                      {
                        "v": "aš₂",
                        "id": "P254894.11.2.1"
                      }
                    ],
                    "cf": "aʾaš",
                    "gw": "wish",
                    "sense": "wish, desire",
                    "norm0": "aʾaš",
                    "pos": "N",
                    "epos": "N",
                    "base": "a₂-aš₂",
                    "morph": "~"
                  },
                  "props": [
                    {
                      "name": "field",
                      "group": "env",
                      "ngram": "-1",
                      "ref": "P254894.11.2"
                    },
                    {
                      "name": "discourse",
                      "group": "env",
                      "value": "body",
                      "ngram": "-1",
                      "ref": "P254894.11.2"
                    }
                  ]
                },
                {
                  "node": "l",
                  "frag": "sa₂",
                  "id": "P254894.l00c1c",
                  "ref": "P254894.11.3",
                  "inst": "sa[equal]",
                  "sig": "@epsd2/literary%sux:sa₂=sa[equal//equal]V/t'V/t$sa/sa₂#~",
                  "f": {
                    "lang": "sux",
                    "form": "sa₂",
                    "delim": "",
                    "gdl": [
                      {
                        "v": "sa₂",
                        "id": "P254894.11.3.0"
                      }
                    ],
                    "cf": "sa",
                    "gw": "equal",
                    "sense": "equal",
                    "norm0": "sa",
                    "pos": "V/t",
                    "epos": "V/t",
                    "base": "sa₂",
                    "morph": "~"
                  },
                  "props": [
                    {
                      "name": "field",
                      "group": "env",
                      "ngram": "-1",
                      "ref": "P254894.11.3"
                    },
                    {
                      "name": "discourse",
                      "group": "env",
                      "value": "body",
                      "ngram": "-1",
                      "ref": "P254894.11.3"
                    }
                  ]
                },
                {
                  "node": "l",
                  "frag": "ed₂-de₃-en",
                  "id": "P254894.l00c1d",
                  "ref": "P254894.11.4",
                  "inst": "e[leave]",
                  "sig": "@epsd2/literary%sux:ed₂-de₃-en=e[leave//to leave, go out]V/i'V/i$e;e.en/e₃+-de₃=d.e#~;e.en",
                  "f": {
                    "lang": "sux",
                    "form": "ed₂-de₃-en",
                    "gdl": [
                      {
                        "v": "ed₂",
                        "id": "P254894.11.4.0",
                        "delim": "-"
                      },
                      {
                        "v": "de₃",
                        "id": "P254894.11.4.1",
                        "delim": "-"
                      },
                      {
                        "v": "en",
                        "id": "P254894.11.4.2"
                      }
                    ],
                    "cf": "e",
                    "gw": "leave",
                    "sense": "to leave, go out",
                    "norm0": "e;e.en",
                    "pos": "V/i",
                    "epos": "V/i",
                    "base": "e₃",
                    "cont": "-de₃=d.e",
                    "morph": "~;e.en"
                  },
                  "props": [
                    {
                      "name": "field",
                      "group": "env",
                      "ngram": "-1",
                      "ref": "P254894.11.4"
                    },
                    {
                      "name": "discourse",
                      "group": "env",
                      "value": "body",
                      "ngram": "-1",
                      "ref": "P254894.11.4"
                    }
                  ]
                },
                {
                  "node": "d",
                  "type": "nonx",
                  "ref": "P254894.12",
                  "strict": "1",
                  "extent": "1",
                  "scope": "line",
                  "state": "ruling"
                },
                {
                  "node": "d",
                  "type": "line-start",
                  "ref": "P254894.13",
                  "n": "8",
                  "label": "o 8"
                },
                {
                  "node": "l",
                  "frag": "šeš-gal",
                  "id": "P254894.l00c1e",
                  "ref": "P254894.13.1",
                  "inst": "šešgal[kinship term]",
                  "sig": "@epsd2/literary%sux:šeš-gal=šešgal[relation//a kinship term, relation]N'N$šešgal/šeš-gal#~",
                  "f": {
                    "lang": "sux",
                    "form": "šeš-gal",
                    "delim": "",
                    "gdl": [
                      {
                        "v": "šeš",
                        "id": "P254894.13.1.0",
                        "delim": "-"
                      },
                      {
                        "v": "gal",
                        "id": "P254894.13.1.1"
                      }
                    ],
                    "cf": "šešgal",
                    "gw": "relation",
                    "sense": "a kinship term, relation",
                    "norm0": "šešgal",
                    "pos": "N",
                    "epos": "N",
                    "base": "šeš-gal",
                    "morph": "~"
                  },
                  "props": [
                    {
                      "name": "field",
                      "group": "env",
                      "ngram": "-1",
                      "ref": "P254894.13.1"
                    },
                    {
                      "name": "discourse",
                      "group": "env",
                      "value": "body",
                      "ngram": "-1",
                      "ref": "P254894.13.1"
                    }
                  ]
                },
                {
                  "node": "l",
                  "frag": "šeš-ban₃-da",
                  "id": "P254894.l00c1f",
                  "ref": "P254894.13.2",
                  "inst": "šešbanda[kinship term]",
                  "sig": "@epsd2/literary%sux:šeš-ban₃-da=šešbanda[relation//a kinship term]N'N$šešbanda/šeš-ban₃-da#~",
                  "f": {
                    "lang": "sux",
                    "form": "šeš-ban₃-da",
                    "delim": "",
                    "gdl": [
                      {
                        "v": "šeš",
                        "id": "P254894.13.2.0",
                        "delim": "-"
                      },
                      {
                        "v": "ban₃",
                        "id": "P254894.13.2.1",
                        "delim": "-"
                      },
                      {
                        "v": "da",
                        "id": "P254894.13.2.2"
                      }
                    ],
                    "cf": "šešbanda",
                    "gw": "relation",
                    "sense": "a kinship term",
                    "norm0": "šešbanda",
                    "pos": "N",
                    "epos": "N",
                    "base": "šeš-ban₃-da",
                    "morph": "~"
                  },
                  "props": [
                    {
                      "name": "field",
                      "group": "env",
                      "ngram": "-1",
                      "ref": "P254894.13.2"
                    },
                    {
                      "name": "discourse",
                      "group": "env",
                      "value": "body",
                      "ngram": "-1",
                      "ref": "P254894.13.2"
                    }
                  ]
                },
                {
                  "node": "l",
                  "frag": "dugud-de-⸢dam⸣",
                  "id": "P254894.l00c20",
                  "ref": "P254894.13.3",
                  "inst": "dugud[heavy]",
                  "sig": "@epsd2/literary%sux:dugud-de-dam=dugud[heavy//(to be) heavy]V/i'V/i$dugud;e.de.am/dugud+-de=d.e#~;e.de.am",
                  "f": {
                    "lang": "sux",
                    "form": "dugud-de-dam",
                    "gdl": [
                      {
                        "v": "dugud",
                        "id": "P254894.13.3.0",
                        "delim": "-"
                      },
                      {
                        "v": "de",
                        "id": "P254894.13.3.1",
                        "delim": "-"
                      },
                      {
                        "v": "dam",
                        "id": "P254894.13.3.2",
                        "break": "damaged",
                        "ho": "1",
                        "hc": "1"
                      }
                    ],
                    "cf": "dugud",
                    "gw": "heavy",
                    "sense": "(to be) heavy",
                    "norm0": "dugud;e.de.am",
                    "pos": "V/i",
                    "epos": "V/i",
                    "base": "dugud",
                    "cont": "-de=d.e",
                    "morph": "~;e.de.am"
                  },
                  "props": [
                    {
                      "name": "field",
                      "group": "env",
                      "ngram": "-1",
                      "ref": "P254894.13.3"
                    },
                    {
                      "name": "discourse",
                      "group": "env",
                      "value": "body",
                      "ngram": "-1",
                      "ref": "P254894.13.3"
                    }
                  ]
                },
                {
                  "node": "d",
                  "type": "line-start",
                  "ref": "P254894.14",
                  "n": "9",
                  "label": "o 9"
                },
                {
                  "node": "l",
                  "frag": "⸢nam⸣-lu₂-lu₇",
                  "id": "P254894.l00c21",
                  "ref": "P254894.14.1",
                  "inst": "namlulu[humanity]",
                  "sig": "@epsd2/literary%sux:nam-lu₂-lu₇=namlulu[humanity//humanity]N'N$namlulu/nam-lu₂-lu₇#~",
                  "f": {
                    "lang": "sux",
                    "form": "nam-lu₂-lu₇",
                    "delim": "",
                    "gdl": [
                      {
                        "v": "nam",
                        "id": "P254894.14.1.0",
                        "break": "damaged",
                        "ho": "1",
                        "delim": "-",
                        "hc": "1"
                      },
                      {
                        "v": "lu₂",
                        "id": "P254894.14.1.1",
                        "delim": "-"
                      },
                      {
                        "v": "lu₇",
                        "id": "P254894.14.1.2"
                      }
                    ],
                    "cf": "namlulu",
                    "gw": "humanity",
                    "sense": "humanity",
                    "norm0": "namlulu",
                    "pos": "N",
                    "epos": "N",
                    "base": "nam-lu₂-lu₇",
                    "morph": "~"
                  },
                  "props": [
                    {
                      "name": "field",
                      "group": "env",
                      "ngram": "-1",
                      "ref": "P254894.14.1"
                    },
                    {
                      "name": "discourse",
                      "group": "env",
                      "value": "body",
                      "ngram": "-1",
                      "ref": "P254894.14.1"
                    }
                  ]
                },
                {
                  "node": "l",
                  "frag": "⸢ak⸣-de₃",
                  "id": "P254894.l00c22",
                  "ref": "P254894.14.2",
                  "inst": "ak[do]",
                  "sig": "@epsd2/literary%sux:ak-de₃=ak[do//do]V/t'V/t$ak;de/ak#~;de",
                  "f": {
                    "lang": "sux",
                    "form": "ak-de₃",
                    "gdl": [
                      {
                        "v": "ak",
                        "id": "P254894.14.2.0",
                        "break": "damaged",
                        "ho": "1",
                        "delim": "-",
                        "hc": "1"
                      },
                      {
                        "v": "de₃",
                        "id": "P254894.14.2.1"
                      }
                    ],
                    "cf": "ak",
                    "gw": "do",
                    "sense": "do",
                    "norm0": "ak;de",
                    "pos": "V/t",
                    "epos": "V/t",
                    "base": "ak",
                    "morph": "~;de"
                  },
                  "props": [
                    {
                      "name": "field",
                      "group": "env",
                      "ngram": "-1",
                      "ref": "P254894.14.2"
                    },
                    {
                      "name": "discourse",
                      "group": "env",
                      "value": "body",
                      "ngram": "-1",
                      "ref": "P254894.14.2"
                    }
                  ]
                },
                {
                  "node": "d",
                  "type": "nonw",
                  "ref": ""
                },
                {
                  "node": "d",
                  "type": "nonx",
                  "ref": "P254894.15",
                  "strict": "1",
                  "extent": "1",
                  "scope": "line",
                  "state": "ruling"
                }
              ]
            }
          ]
        }
      ]
    },
    {
      "linkbase": [
        {
          "type": "linkset",
          "xlink_title": "šu gi[repay//to repay]V/t'V/t",
          "id": "P254894.ls00000",
          "xlink_type": "extended",
          "xlink_role": "psu",
          "sig": "{šu-a gi₄-gi₄-de₃ = šu[hand]N gi[turn]V/i += šu gi[repay//to repay]V/t'V/t}::@epsd2/literary%sux:šu-a=šu[hand//hand]N'N$šu,a/šu#~,a++@epsd2/literary%sux:gi₄-gi₄-de₃=gi[turn//turn]V/i'V/i$gi;de/gi₄-gi₄#~;de",
          "links": [
            {
              "type": "link",
              "xlink_title": "šu",
              "xlink_type": "locator",
              "xlink_href": "#P254894.l00c0b",
              "xlink_role": "elt"
            },
            {
              "type": "link",
              "xlink_title": "gi",
              "xlink_type": "locator",
              "xlink_href": "#P254894.l00c0c",
              "xlink_role": "elt"
            }
          ]
        },
        {
          "type": "linkset",
          "xlink_title": "ni teŋ[fear//to fear, to become afraid]V/t'V/t",
          "id": "P254894.ls00001",
          "xlink_type": "extended",
          "xlink_role": "psu",
          "sig": "{ni₂ teŋ₃-ŋa₂ = ni[fear]N teŋ[near]V/i += ni teŋ[fear//to fear, to become afraid]V/t'V/t}::@epsd2/literary%sux:ni₂=ni[fear//aura]N'N$ni/ni₂#~++@epsd2/literary%sux:teŋ₃-ŋa₂=teŋ[near//to approach]V/i'V/t$teŋ;a/teŋ₃+-ŋa₂=ŋ.a#~;a",
          "links": [
            {
              "type": "link",
              "xlink_title": "ni",
              "xlink_type": "locator",
              "xlink_href": "#P254894.l00c12",
              "xlink_role": "elt"
            },
            {
              "type": "link",
              "xlink_title": "teŋ",
              "xlink_type": "locator",
              "xlink_href": "#P254894.l00c13",
              "xlink_role": "elt"
            }
          ]
        }
      ]
    }
  ]
}
